<annotation>
	<folder>Basler_acA2040_90umNIR__22896797__20190215_154914404_mp4</folder>
	<filename>img0015.jpg</filename>
	<path>/Users/sarahconstantin/Downloads/Basler_acA2040_90umNIR__22896797__20190215_154914404_mp4/img0015.jpg</path>
	<source>
		<database>Unknown</database>
	</source>
	<size>
		<width>2048</width>
		<height>2048</height>
		<depth>1</depth>
	</size>
	<segmented>0</segmented>
	<object>
		<name>Daphnia</name>
		<pose>Unspecified</pose>
		<truncated>0</truncated>
		<difficult>0</difficult>
		<bndbox>
			<xmin>786</xmin>
			<ymin>1197</ymin>
			<xmax>843</xmax>
			<ymax>1249</ymax>
		</bndbox>
	</object>
	<object>
		<name>Daphnia</name>
		<pose>Unspecified</pose>
		<truncated>0</truncated>
		<difficult>0</difficult>
		<bndbox>
			<xmin>748</xmin>
			<ymin>1166</ymin>
			<xmax>803</xmax>
			<ymax>1215</ymax>
		</bndbox>
	</object>
	<object>
		<name>Daphnia</name>
		<pose>Unspecified</pose>
		<truncated>0</truncated>
		<difficult>0</difficult>
		<bndbox>
			<xmin>652</xmin>
			<ymin>1152</ymin>
			<xmax>680</xmax>
			<ymax>1194</ymax>
		</bndbox>
	</object>
	<object>
		<name>Daphnia</name>
		<pose>Unspecified</pose>
		<truncated>0</truncated>
		<difficult>0</difficult>
		<bndbox>
			<xmin>729</xmin>
			<ymin>1237</ymin>
			<xmax>766</xmax>
			<ymax>1271</ymax>
		</bndbox>
	</object>
	<object>
		<name>Daphnia</name>
		<pose>Unspecified</pose>
		<truncated>0</truncated>
		<difficult>0</difficult>
		<bndbox>
			<xmin>809</xmin>
			<ymin>1255</ymin>
			<xmax>832</xmax>
			<ymax>1294</ymax>
		</bndbox>
	</object>
	<object>
		<name>Daphnia</name>
		<pose>Unspecified</pose>
		<truncated>0</truncated>
		<difficult>0</difficult>
		<bndbox>
			<xmin>995</xmin>
			<ymin>1154</ymin>
			<xmax>1015</xmax>
			<ymax>1185</ymax>
		</bndbox>
	</object>
	<object>
		<name>Daphnia</name>
		<pose>Unspecified</pose>
		<truncated>0</truncated>
		<difficult>0</difficult>
		<bndbox>
			<xmin>1057</xmin>
			<ymin>1142</ymin>
			<xmax>1074</xmax>
			<ymax>1177</ymax>
		</bndbox>
	</object>
	<object>
		<name>Daphnia</name>
		<pose>Unspecified</pose>
		<truncated>0</truncated>
		<difficult>0</difficult>
		<bndbox>
			<xmin>1094</xmin>
			<ymin>1169</ymin>
			<xmax>1135</xmax>
			<ymax>1211</ymax>
		</bndbox>
	</object>
	<object>
		<name>Daphnia</name>
		<pose>Unspecified</pose>
		<truncated>0</truncated>
		<difficult>0</difficult>
		<bndbox>
			<xmin>1246</xmin>
			<ymin>1165</ymin>
			<xmax>1278</xmax>
			<ymax>1189</ymax>
		</bndbox>
	</object>
	<object>
		<name>Daphnia</name>
		<pose>Unspecified</pose>
		<truncated>0</truncated>
		<difficult>0</difficult>
		<bndbox>
			<xmin>1334</xmin>
			<ymin>1157</ymin>
			<xmax>1397</xmax>
			<ymax>1202</ymax>
		</bndbox>
	</object>
	<object>
		<name>Daphnia</name>
		<pose>Unspecified</pose>
		<truncated>0</truncated>
		<difficult>0</difficult>
		<bndbox>
			<xmin>1478</xmin>
			<ymin>1174</ymin>
			<xmax>1535</xmax>
			<ymax>1249</ymax>
		</bndbox>
	</object>
</annotation>
